get_files_list/__init__.py
get_files_list/get_dir_content.py
get_files_list-0.3.1.dist-info/licenses/LICENSE
get_files_list-0.3.1.dist-info/METADATA
get_files_list-0.3.1.dist-info/WHEEL
get_files_list-0.3.1.dist-info/top_level.txt
get_files_list-0.3.1.dist-info/RECORD
