Metadata-Version: 2.4
Name: get_files_list
Version: 0.3.1
Summary: Python package that provides a utility function to recursively get files that match a pattern
Home-page: https://github.com/LucaAngioloni/get_files_list
Author: Luca Angioloni
Author-email: lucaangioloni@gmail.com
License: MIT License
Project-URL: Source, https://github.com/LucaAngioloni/get_files_list
Project-URL: Issues, https://github.com/LucaAngioloni/get_files_list/issues
Project-URL: Changelog, https://github.com/LucaAngioloni/get_files_list/releases
Keywords: files,get_files_list,recursive,pattern,match,file list
Classifier: Intended Audience :: Developers
Classifier: Intended Audience :: Other Audience
Classifier: Intended Audience :: System Administrators
Classifier: Operating System :: OS Independent
Classifier: Programming Language :: Python :: 3
Classifier: Topic :: Utilities
License-File: LICENSE
Dynamic: author
Dynamic: author-email
Dynamic: classifier
Dynamic: description
Dynamic: description-content-type
Dynamic: home-page
Dynamic: keywords
Dynamic: license
Dynamic: license-file
Dynamic: project-url
Dynamic: summary
